eero/__init__.py
eero/logger.py
eero/py.typed
eero/version.py
eero/client/__init__.py
eero/client/api_client.py
eero/client/clients/__init__.py
eero/client/clients/eero.py
eero/client/clients/eero_auth_handler.py
eero/client/clients/network.py
eero/client/models/__init__.py
eero/client/models/ac_compat.py
eero/client/models/account.py
eero/client/models/burst_reporters.py
eero/client/models/device.py
eero/client/models/diagnostics.py
eero/client/models/error_meta.py
eero/client/models/forward.py
eero/client/models/networks.py
eero/client/models/no_data_meta.py
eero/client/models/profile.py
eero/client/models/reservation.py
eero/client/models/routing.py
eero/client/models/speedtest.py
eero/client/models/support.py
eero/client/models/thread.py
eero/client/models/updates.py
eero/client/routes/__init__.py
eero/client/routes/method_factory.py
eero/client/routes/routes.py
eero/exceptions/__init__.py
eero/exceptions/client_exception.py
eero/session/__init__.py
eero/session/abc.py
eero/session/file.py
eero/session/memory.py
eero_client-2.2.1.dist-info/LICENSE
eero_client-2.2.1.dist-info/METADATA
eero_client-2.2.1.dist-info/WHEEL
eero_client-2.2.1.dist-info/top_level.txt
eero_client-2.2.1.dist-info/RECORD
