Metadata-Version: 2.1
Name: eero-client
Version: 2.2.1
Summary: Manage eero network devices
Home-page: https://github.com/EvanSchalton/eero-client
Author: Evan Schalton
Author-email: Evan.Schalton@Gmail.com
License: MIT License
Keywords: eero
Classifier: Development Status :: 4 - Beta
Classifier: Intended Audience :: Developers
Classifier: Natural Language :: English
Classifier: Operating System :: OS Independent
Classifier: Programming Language :: Python :: 3
Classifier: Programming Language :: Python :: 3.10
Classifier: Programming Language :: Python :: 3.11
Classifier: Typing :: Typed
Classifier: Topic :: Software Development :: Libraries :: Python Modules
Classifier: Topic :: Utilities
Classifier: License :: OSI Approved :: MIT License
Requires-Python: >=3.10
License-File: LICENSE
Requires-Dist: annotated-types==0.7.0
Requires-Dist: certifi==2024.7.4
Requires-Dist: charset-normalizer==3.3.2
Requires-Dist: idna==3.7
Requires-Dist: pydantic==2.8.2
Requires-Dist: pydantic-core==2.20.1
Requires-Dist: requests==2.32.3
Requires-Dist: types-requests==2.32.0.20240712
Requires-Dist: typing-extensions==4.12.2
Requires-Dist: urllib3==2.2.2
